scrapy_selenium/__init__.py
scrapy_selenium/http.py
scrapy_selenium/middlewares.py
scrapy_selenium/selenium_utilities.py
tests/__init__.py
tests/test_cases.py
tests/test_middlewares.py
scrapy_selenium_mm-0.1.1.dist-info/LICENCE
scrapy_selenium_mm-0.1.1.dist-info/METADATA
scrapy_selenium_mm-0.1.1.dist-info/WHEEL
scrapy_selenium_mm-0.1.1.dist-info/top_level.txt
scrapy_selenium_mm-0.1.1.dist-info/RECORD
