Metadata-Version: 2.1
Name: scrapy-selenium-mm
Version: 0.1.1
Summary: Scrapy with selenium
Home-page: https://github.com/clemfromspace/scrapy-selenium
License-File: LICENCE
Requires-Dist: scrapy >=1.0.0
Requires-Dist: selenium >=3.9.0
